mecab_text_cleaner/__init__.py
mecab_text_cleaner/__main__.py
mecab_text_cleaner/_main.py
mecab_text_cleaner/cli.py
mecab_text_cleaner/py.typed
mecab_text_cleaner-0.1.1.dist-info/LICENSE
mecab_text_cleaner-0.1.1.dist-info/METADATA
mecab_text_cleaner-0.1.1.dist-info/WHEEL
mecab_text_cleaner-0.1.1.dist-info/entry_points.txt
mecab_text_cleaner-0.1.1.dist-info/RECORD
