Metadata-Version: 2.1
Name: mecab-text-cleaner
Version: 0.1.1
Summary: Simple Python package for getting japanese reading (yomigana) using MeCab
Home-page: https://github.com/34j/mecab-text-cleaner
License: MIT
Author: 34j
Author-email: 34j.95a2p@simplelogin.com
Requires-Python: >=3.8,<4.0
Classifier: Development Status :: 2 - Pre-Alpha
Classifier: Intended Audience :: Developers
Classifier: License :: OSI Approved :: MIT License
Classifier: Natural Language :: English
Classifier: Operating System :: OS Independent
Classifier: Programming Language :: Python :: 3
Classifier: Programming Language :: Python :: 3.8
Classifier: Programming Language :: Python :: 3.9
Classifier: Programming Language :: Python :: 3.10
Classifier: Programming Language :: Python :: 3.11
Classifier: Programming Language :: Python :: 3.12
Classifier: Topic :: Software Development :: Libraries
Requires-Dist: attrs (>=23.1.0,<24.0.0)
Requires-Dist: click (>=8.1.7,<9.0.0)
Requires-Dist: fugashi[unidic-lite] (>=1.3.0,<2.0.0)
Project-URL: Bug Tracker, https://github.com/34j/mecab-text-cleaner/issues
Project-URL: Changelog, https://github.com/34j/mecab-text-cleaner/blob/main/CHANGELOG.md
Project-URL: Documentation, https://mecab-text-cleaner.readthedocs.io
Project-URL: Repository, https://github.com/34j/mecab-text-cleaner
